setup.py
django_ueditor_plugin.egg-info/PKG-INFO
django_ueditor_plugin.egg-info/SOURCES.txt
django_ueditor_plugin.egg-info/dependency_links.txt
django_ueditor_plugin.egg-info/entry_points.txt
django_ueditor_plugin.egg-info/pbr.json
django_ueditor_plugin.egg-info/requires.txt
django_ueditor_plugin.egg-info/top_level.txt
django_ueditor_plugin.egg-info/zip-safe
ueditor/__init__.py
ueditor/admin.py
ueditor/config.py
ueditor/models.py
ueditor/tests.py
ueditor/urls.py
ueditor/utils.py
ueditor/views.py
ueditor/migrations/0001_initial.py
ueditor/migrations/0002_ueditorfile_status.py
ueditor/migrations/__init__.py