Metadata-Version: 1.1
Name: django-ueditor-plugin
Version: 0.13
Summary: a backend plugin for ueditor
Home-page: https://github.com/youngershen/django-ueditor-plugin
Author: younger shen
Author-email: younger.x.shen@gmail.com
License: MIT
Keywords: django-ueditor-plugin,django,ueditor
Platform: UNKNOWN
Classifier: Development Status :: 2 - Pre-Alpha
Classifier: Environment :: Web Environment
Classifier: Framework :: Django
Classifier: Intended Audience :: Developers
Classifier: License :: OSI Approved :: MIT License
Classifier: Natural Language :: English
Classifier: Programming Language :: Python :: 2.7
